Structural Modeling/04_Full_Subtractor/Full_Subtractor/Full_Subtractor.v
// Date: 07/01/2026
// Autor: Alan Gomez
// Module: Full_Subtractor
// --------------------------------------------------

module Full_Subtractor (
    input a, b, Bin,// Inputs
    output D, Bout// Outputs
);

    assign D = a ^ b ^ Bin;
    assign Bout = (!a & b) | (!(a ^ b) & Bin);

endmodule

Structural Modeling/04_Full_Subtractor/Full_Subtractor_with_Half_Subtractor/Full_Subtractor_tb.v
// Date: 07/01/2026
// Autor: Alan Gomez
// Module: Full_Subtractor_tb.v
// --------------------------------------------------

module Full_Subtractor_tb;
    reg a, b, Bin;        // Test inputs
    wire D, Bout;    // Test outputs

    // Instantiate the Full_Subtractor
    Full_Subtractor U1(
        .a(a),
        .b(b),
        .Bin(Bin),
        .D(D),
        .Bout(Bout)
    );

    initial begin
        // Set up VCD dump file for waveform viewing
        $dumpfile("waveform.vcd");
        $dumpvars(0, Full_Subtractor_tb);

        // Monitor changes in signals
        $monitor("At time %0t: a=%b b=%b, Bin=%b, Difference=%b, Borrow_out=%b", $time, a, b, Bin, D, Bout);

        // Test all input combinations
        a = 0;
        b = 0;
        Bin = 0;
        #40 $finish; // Finish Simulation
    end
    always #20 a = ~a; // Square wave with period 40
    always #10 b = ~b; // Square wave with period 20
    always #5 Bin = ~Bin; // Square wave with period 10

endmodule

Structural Modeling/04_Full_Subtractor/Full_Subtractor/waveform.vcd
$date
	Wed Jan  7 21:39:52 2026
$end
$version
	Icarus Verilog
$end
$timescale
	1s
$end
$scope module Full_Subtractor_tb $end
$var wire 1 ! D $end
$var wire 1 " Bout $end
$var reg 1 # Bin $end
$var reg 1 $ a $end
$var reg 1 % b $end
$scope module U1 $end
$var wire 1 # Bin $end
$var wire 1 " Bout $end
$var wire 1 ! D $end
$var wire 1 $ a $end
$var wire 1 % b $end
$upscope $end
$upscope $end
$enddefinitions $end
$comment Show the parameter values. $end
$dumpall
$end
#0
$dumpvars
0%
0$
0#
0"
0!
$end
#5
1"
1!
1#
#10
0#
1%
#15
0!
1#
#20
0"
1!
0#
0%
1$
#25
0!
1#
#30
0#
1%
#35
1"
1!
1#
#40
0"
0!
0#
0%
0$
