Structural Modeling/2_Full_Adder/Full_Adder/Full_Adder.v
// Full Adder in Verilog
// Combinational circuit
// Date: 01/07/2026

module Full_Adder(
    input a, b, cin, // a - bit 1, b - bit 2, cin - carry input
    output S, Cout // S - output, Cout -  Carry output
);
    assign S = a ^ b ^ cin;
    assign Cout = (a & b) | (b & cin) | (a & cin); 
endmodule

Structural Modeling/02_Full_Adder/Full_Adder/Full_Adder_tb.v
// Full Adder testbench in Verilog
// Combinational circuit
// Date: 01/07/2026
module Full_Adder_tb;
reg a, b, cin;
wire S, Cout;

// interconnection modules.

Full_Adder U1(
    .a(a),
    .b(b),
    .cin(cin),
    .S(S),
    .Cout(Cout)
);

initial begin
   // Set up VCD dump file for waveform viewing
    $dumpfile("waveform.vcd");
    $dumpvars(0, Full_Adder_tb); 
    // Monitor changes in signals
    $monitor("At time %0t: | a=%b. b=%b. cin=%b. | S=%b. Cout=%b.", $time, a, b, cin, S, Cout);
    // Test all input combinations
    a = 0; b = 0; cin = 0; #1;
    a = 0; b = 0; cin = 1; #1;
    a = 0; b = 1; cin = 0; #1;
    a = 0; b = 1; cin = 1; #1;
    a = 1; b = 0; cin = 0; #1;
    a = 1; b = 0; cin = 1; #1;
    a = 1; b = 1; cin = 0; #1;
    a = 1; b = 1; cin = 1; #1;
end
    
endmodule

Structural Modeling/02_Full_Adder/Full_Adder/waveform.vcd
$date
	Wed Jan  7 14:45:28 2026
$end
$version
	Icarus Verilog
$end
$timescale
	1s
$end
$scope module Full_Adder_tb $end
$var wire 1 ! S $end
$var wire 1 " Cout $end
$var reg 1 # a $end
$var reg 1 $ b $end
$var reg 1 % cin $end
$scope module U1 $end
$var wire 1 " Cout $end
$var wire 1 ! S $end
$var wire 1 # a $end
$var wire 1 $ b $end
$var wire 1 % cin $end
$upscope $end
$upscope $end
$enddefinitions $end
$comment Show the parameter values. $end
$dumpall
$end
#0
$dumpvars
0%
0$
0#
0"
0!
$end
#1
1!
1%
#2
0%
1$
#3
1"
0!
1%
#4
0"
1!
0%
0$
1#
#5
1"
0!
1%
#6
0%
1$
#7
1!
1%
