Structural Modeling/05_2_Carry_Look_Ahead/Carry_Look_Ahead.v
// Carry_Look_Ahead_Adder
// de 8bits.
// by Alan Gomez

module FullAdder(
    input A,// Entrada A
    input B,// Entrada B
    input Cin,// Carry de entrada
    output S// Resultado de suma
    //output Pi,
    //output Gi
);
wire w;
// Conexiones
assign w = A ^ B;
assign S = w ^ Cin;// Resultado final
//assign Pi = A | B;
//assign Gi = A & B;
// No hay Cout ya que vamos a predecir el carry
endmodule

module CLA(
    input [7:0] A, // Entrada A de 8bits
    input [7:0] B, // Entrada B de 8bits
    output [31:0] S // Salida de 2 bits
);
wire [7:0] P;// Se propagó un carry?
wire [7:0] G;// Se generó un carry?
wire [8:0] C;// Carry de 9 bits el bit 8 de la salida será el último carry.

assign P = A | B;// Se conecta salida P de 8bits
assign G = A & B;// Se conecta salida G de 8bits

// Se calculan el carry de 9bits menos el C0 que es 0. Por carry inicial.
assign C[1] = G[0] | P[0] & 1'b0;
assign C[2] = G[1] | P[1] & G[0] | P[1] & P[0] & 1'b0;
assign C[3] = G[2] | P[2] & G[1] | P[2] & P[1] & G[0] | P[2] & P[1] & P[0] & 1'b0;
assign C[4] = G[3] | P[3] & G[2] | P[3] & P[2] & G[1] | P[3] & P[2] & P[1] & G[0] | P[3] & P[2] & P[1] & P[0] & 1'b0;
assign C[5] = G[4] | P[4] & G[3] | P[4] & P[3] & G[2] | P[4] & P[3] & P[2] & G[1] | P[4] & P[3] & P[2] & P[1] & G[0] | P[4] & P[3] & P[2] & P[1] & P[0] & 1'b0;
assign C[6] = G[5] | P[5] & G[4] | P[5] & P[4] & G[3] | P[5] & P[4] & P[3] & G[2] | P[5] & P[4] & P[3] & P[2] & G[1] | P[5] & P[4] & P[3] & P[2] & P[1] & G[0] | P[5] & P[4] & P[3] & P[2] & P[1] & P[0] & 1'b0;
assign C[7] = G[6] | P[6] & G[5] | P[6] & P[5] & G[4] | P[6] & P[5] & P[4] & G[3] | P[6] & P[5] & P[4] & P[3] & G[2] | P[6] & P[5] & P[4] & P[3] & P[2] & G[1] | P[6] & P[5] & P[4] & P[3] & P[2] & P[1] & G[0] | P[6] & P[5] & P[4] & P[3] & P[2] & P[1] & P[0] & 1'b0;
assign C[8] = G[7] | P[7] & G[6] | P[7] & P[6] & G[5] | P[7] & P[6] & P[5] & G[4] | P[7] & P[6] & P[5] & P[4] & G[3] | P[7] & P[6] & P[5] & P[4] & P[3] & G[2] | P[7] & P[6] & P[5] & P[4] & P[3] & P[2] & G[1] | P[7] & P[6] & P[5] & P[4] & P[3] & P[2] & P[1] & G[0] | P[7] & P[6] & P[5] & P[4] & P[3] & P[2] & P[1] & P[0] & 1'b0;
// Conexiones para de 8 Full adder de un bit para de uno de 8 bits
FullAdder FA1(.A(A[0]), .B(B[0]), .Cin(1'b0), .S(S[0]));
FullAdder FA2(.A(A[1]), .B(B[1]), .Cin(C[1]), .S(S[1]));
FullAdder FA3(.A(A[2]), .B(B[2]), .Cin(C[2]), .S(S[2]));
FullAdder FA4(.A(A[3]), .B(B[3]), .Cin(C[3]), .S(S[3]));
FullAdder FA5(.A(A[4]), .B(B[4]), .Cin(C[4]), .S(S[4]));
FullAdder FA6(.A(A[5]), .B(B[5]), .Cin(C[5]), .S(S[5]));
FullAdder FA7(.A(A[6]), .B(B[6]), .Cin(C[6]), .S(S[6]));
FullAdder FA8(.A(A[7]), .B(B[7]), .Cin(C[7]), .S(S[7]));

assign S[8] = C[8]; // El noveno bit de S es el carry del sumador de 8bits

assign S[31:9] = 23'b0;// el resto de bits del resultado son 0

endmodule

// REF 
//[1] “Ripple Carry Adder - COMPUTER SCIENCE BYTES,” COMPUTER SCIENCE BYTES, Jul. 12, 2017.
//     https://www.computersciencebytes.com/boolean-logic/ripple-carry-adder/ (accessed Sep. 01, 2025).
//[2] admin, “Carry Look Ahead Adder Verilog Code | 16 bit Carry Look Ahead Adder Verilog Implementation,” 
//    VLSI GYAN, Sep. 2017. https://vlsigyan.com/16-bit-carry-look-ahead-adder-verilog/ (accessed Sep. 01, 2025).
‌

Structural Modeling/05_2_Carry_Look_Ahead/Carry_Look_Ahead_tb.v
// Date: 07/01/2026
// Autor: Alan Gomez
// Module: Ripple_Carry_Adder_tb.v
// --------------------------------------------------

module CLA_tb;

    // Entradas
    reg [7:0] A;
    reg [7:0] B;

    // Salidas
    wire [31:0] SUM;

    // Variables de tiempo
    time start, finish;

    // Instancia del DUT (Device Under Test)
    CLA uut (
        .A(A),
        .B(B),
        .S(SUM)
    );

    initial begin
        // Generar archivo de ondas para GTKWave (opcional)
        $dumpfile("waveform.vcd");
        $dumpvars(0, CLA_tb);

        // Caso 1
        A = 0; B = 0;
        start = $time;
        #1; // esperar que la salida se estabilice
        finish = $time;
        $display("Time=%0t | A=%b (%0d), B=%b (%0d) -> SUM=%b (%0d), Cout=%b",
                 finish, A, A, B, B, SUM, SUM, SUM[8]);
        // Caso 2
        A = 1; B = 1;
        start = $time;
        #1;
        finish = $time;
        $display("Time=%0t | A=%b (%0d), B=%b (%0d) -> SUM=%b (%0d), Cout=%b",
                 finish, A, A, B, B, SUM, SUM, SUM[8]);
        // Caso 3
        A = 255; B = 1;
        start = $time;
        #1;
        finish = $time;
        $display("Time=%0t | A=%b (%0d), B=%b (%0d) -> SUM=%b (%0d), Cout=%b",
                 finish, A, A, B, B, SUM, SUM, SUM[8]);
        // Caso 4
        A = 10; B = 5;
        start = $time;
        #1;
        finish = $time;
        $display("Time=%0t | A=%b (%0d), B=%b (%0d) -> SUM=%b (%0d), Cout=%b",
                 finish, A, A, B, B, SUM, SUM, SUM[8]);
        // Caso 5
        A = 127; B = 1;
        start = $time;
        #1;
        finish = $time;
        $display("Time=%0t | A=%b (%0d), B=%b (%0d) -> SUM=%b (%0d), Cout=%b",
                 finish, A, A, B, B, SUM, SUM, SUM[8]);
        // Caso 6
        A = 240; B = 15;
        start = $time;
        #1;
        finish = $time;
        $display("Time=%0t | A=%b (%0d), B=%b (%0d) -> SUM=%b (%0d), Cout=%b",
                 finish, A, A, B, B, SUM, SUM, SUM[8]);
        // Caso 7
        A = 5; B = 3;
        start = $time;
        #1;
        finish = $time;
        $display("Time=%0t | A=%b (%0d), B=%b (%0d) -> SUM=%b (%0d), Cout=%b",
                 finish, A, A, B, B, SUM, SUM, SUM[8]);
        // Caso 8
        A = 170; B = 85;
        start = $time;
        #1;
        finish = $time;
        $display("Time=%0t | A=%b (%0d), B=%b (%0d) -> SUM=%b (%0d), Cout=%b",
                 finish, A, A, B, B, SUM, SUM, SUM[8]);
        // Caso 9
        A = 0; B = 85;
        start = $time;
        #1;
        finish = $time;
        $display("Time=%0t | A=%b (%0d), B=%b (%0d) -> SUM=%b (%0d), Cout=%b",
                 finish, A, A, B, B, SUM, SUM, SUM[8]);
        // Caso 10
        A = 255; B = 255;
        start = $time;
        #1;
        finish = $time;
        $display("Time=%0t | A=%b (%0d), B=%b (%0d) -> SUM=%b (%0d), Cout=%b",
                 finish, A, A, B, B, SUM, SUM, SUM[8]);
        // Finalizar simulación
        #10 $finish;
    end

endmodule

Structural Modeling/05_2_Carry_Look_Ahead/waveform.vcd
$date
	Thu Jan  8 00:23:35 2026
$end
$version
	Icarus Verilog
$end
$timescale
	1s
$end
$scope module CLA_tb $end
$var wire 32 ! SUM [31:0] $end
$var reg 8 " A [7:0] $end
$var reg 8 # B [7:0] $end
$var reg 64 $ finish [63:0] $end
$var reg 64 % start [63:0] $end
$scope module uut $end
$var wire 8 & A [7:0] $end
$var wire 8 ' B [7:0] $end
$var wire 8 ( G [7:0] $end
$var wire 8 ) P [7:0] $end
$var wire 32 * S [31:0] $end
$var wire 9 + C [8:0] $end
$scope module FA1 $end
$var wire 1 , A $end
$var wire 1 - B $end
$var wire 1 . Cin $end
$var wire 1 / S $end
$var wire 1 0 w $end
$upscope $end
$scope module FA2 $end
$var wire 1 1 A $end
$var wire 1 2 B $end
$var wire 1 3 Cin $end
$var wire 1 4 S $end
$var wire 1 5 w $end
$upscope $end
$scope module FA3 $end
$var wire 1 6 A $end
$var wire 1 7 B $end
$var wire 1 8 Cin $end
$var wire 1 9 S $end
$var wire 1 : w $end
$upscope $end
$scope module FA4 $end
$var wire 1 ; A $end
$var wire 1 < B $end
$var wire 1 = Cin $end
$var wire 1 > S $end
$var wire 1 ? w $end
$upscope $end
$scope module FA5 $end
$var wire 1 @ A $end
$var wire 1 A B $end
$var wire 1 B Cin $end
$var wire 1 C S $end
$var wire 1 D w $end
$upscope $end
$scope module FA6 $end
$var wire 1 E A $end
$var wire 1 F B $end
$var wire 1 G Cin $end
$var wire 1 H S $end
$var wire 1 I w $end
$upscope $end
$scope module FA7 $end
$var wire 1 J A $end
$var wire 1 K B $end
$var wire 1 L Cin $end
$var wire 1 M S $end
$var wire 1 N w $end
$upscope $end
$scope module FA8 $end
$var wire 1 O A $end
$var wire 1 P B $end
$var wire 1 Q Cin $end
$var wire 1 R S $end
$var wire 1 S w $end
$upscope $end
$upscope $end
$upscope $end
$enddefinitions $end
$comment Show the parameter values. $end
$dumpall
$end
#0
$dumpvars
0S
0R
0Q
0P
0O
0N
0M
0L
0K
0J
0I
0H
0G
0F
0E
0D
0C
0B
0A
0@
0?
0>
0=
0<
0;
0:
09
08
07
06
05
04
03
02
01
00
0/
0.
0-
0,
b0z +
b0 *
b0 )
b0 (
b0 '
b0 &
b0 %
bx $
b0 #
b0 "
b0 !
$end
#1
b10 !
b10 *
14
13
b1z +
1-
b1 )
b1 (
1,
b1 %
b1 #
b1 '
b1 "
b1 &
b1 $
#2
1Q
1L
1G
1B
1=
18
b11111111z +
04
09
0>
0C
0H
0M
b100000000 !
b100000000 *
0R
15
1:
1?
1D
1I
1N
1S
b11111111 )
11
16
1;
1@
1E
1J
1O
b10 %
b11111111 "
b11111111 &
b10 $
#3
19
1>
08
0=
0B
0G
0L
0Q
14
03
b0z +
1/
0C
0H
0M
b1111 !
b1111 *
0R
10
0D
0I
0N
0S
17
b1111 )
b0 (
0,
06
0@
0E
0J
0O
b11 %
b101 #
b101 '
b1010 "
b1010 &
b11 $
#4
1R
1Q
1L
1G
09
0>
18
1=
1B
04
13
b1111111z +
0/
0C
0H
b10000000 !
b10000000 *
0M
00
1D
1I
1N
07
b1111111 )
b1 (
1,
16
1@
1E
1J
b100 %
b1 #
b1 '
b1111111 "
b1111111 &
b100 $
#5
19
1>
1C
1H
1M
08
0=
0B
0G
0L
0Q
14
03
b0z +
1/
b11111111 !
b11111111 *
1R
10
1S
12
17
1<
b11111111 )
b0 (
0,
01
06
0;
1O
b101 %
b1111 #
b1111 '
b11110000 "
b11110000 &
b101 $
#6
09
18
1=
0B
0G
0L
0Q
04
13
1>
b111z +
0/
0C
0H
0M
b1000 !
b1000 *
0R
0?
00
0D
0I
0N
0S
07
0<
b111 )
b1 (
1,
16
0@
0E
0J
0O
b110 %
b11 #
b11 '
b101 "
b101 &
b110 $
#7
19
08
0=
14
03
1C
1M
b0z +
1/
1>
1H
b11111111 !
b11111111 *
1R
1D
1N
10
1?
1I
1S
02
17
1A
1K
b11111111 )
b0 (
0,
11
06
1;
1E
1O
b111 %
b1010101 #
b1010101 '
b10101010 "
b10101010 &
b111 $
#8
04
0>
0H
b1010101 !
b1010101 *
0R
05
0?
0I
0S
b1010101 )
01
0;
0E
0O
b1000 %
b0 "
b0 &
b1000 $
#9
1R
1Q
1H
1L
1G
1>
1B
1=
14
18
13
b11111111z +
0/
19
1C
b111111110 !
b111111110 *
1M
00
0:
0D
0N
12
1<
1F
1P
b11111111 )
b11111111 (
1,
11
16
1;
1@
1E
1J
1O
b1001 %
b11111111 #
b11111111 '
b11111111 "
b11111111 &
b1001 $
#10
b1010 $
